oofempostpy/__init__.py
oofempostpy/extract.py
oofempostpy/hm2mole2d.py
oofempostpy/hm2mole3d.py
oofempostpy/hm2of.py
oofempostpy/hm2of2d.py
oofempostpy/hm2of3d.py
oofempostpy/hm2of_matset.py
oofempostpy/parser.py
oofempostpy/sectmat.py
oofempostpy/timeCount.py
oofempostpy-0.1.7.dist-info/LICENSE
oofempostpy-0.1.7.dist-info/METADATA
oofempostpy-0.1.7.dist-info/WHEEL
oofempostpy-0.1.7.dist-info/top_level.txt
oofempostpy-0.1.7.dist-info/RECORD
